mp3tag/__init__.py
mp3tag/id3tag.py
mp3tag/musictag.py
mp3tag-0.0.4.dist-info/LICENSE
mp3tag-0.0.4.dist-info/METADATA
mp3tag-0.0.4.dist-info/WHEEL
mp3tag-0.0.4.dist-info/top_level.txt
mp3tag-0.0.4.dist-info/RECORD
