Metadata-Version: 2.1
Name: mp3tag
Version: 0.0.4
Summary: MP3 tag information reader and writer.
Home-page: https://github.com/cocowool/mp3tag
Author: Wang Shiqiang
Author-email: cocowool@qq.com
Project-URL: Bug Tracker, https://github.com/cocowool/mp3tag/issues
Keywords: mp3,id3,id3v2
Requires-Python: >=3.6
License-File: LICENSE
